telliot_feeds/__init__.py
telliot_feeds/__main__.py
telliot_feeds/constants.py
telliot_feeds/datafeed.py
telliot_feeds/datasource.py
telliot_feeds/cli/__init__.py
telliot_feeds/cli/constants.py
telliot_feeds/cli/main.py
telliot_feeds/cli/utils.py
telliot_feeds/cli/commands/__init__.py
telliot_feeds/cli/commands/account.py
telliot_feeds/cli/commands/catalog.py
telliot_feeds/cli/commands/config.py
telliot_feeds/cli/commands/integrations.py
telliot_feeds/cli/commands/liquity.py
telliot_feeds/cli/commands/query.py
telliot_feeds/cli/commands/report.py
telliot_feeds/cli/commands/request_withdraw_stake.py
telliot_feeds/cli/commands/settle.py
telliot_feeds/cli/commands/stake.py
telliot_feeds/cli/commands/tip.py
telliot_feeds/cli/commands/withdraw.py
telliot_feeds/dtypes/__init__.py
telliot_feeds/dtypes/datapoint.py
telliot_feeds/dtypes/float_type.py
telliot_feeds/dtypes/value_type.py
telliot_feeds/feeds/__init__.py
telliot_feeds/feeds/aave_usd_feed.py
telliot_feeds/feeds/albt_usd_feed.py
telliot_feeds/feeds/ampl_usd_vwap_feed.py
telliot_feeds/feeds/avax_usd_feed.py
telliot_feeds/feeds/badger_usd_feed.py
telliot_feeds/feeds/bch_usd_feed.py
telliot_feeds/feeds/bct_usd_feed.py
telliot_feeds/feeds/brl_usd_feed.py
telliot_feeds/feeds/btc_usd_feed.py
telliot_feeds/feeds/cbeth_usd_feed.py
telliot_feeds/feeds/cny_usd_feed.py
telliot_feeds/feeds/comp_usd_feed.py
telliot_feeds/feeds/crv_usd_feed.py
telliot_feeds/feeds/custom_price_manual_feed.py
telliot_feeds/feeds/dai_usd_feed.py
telliot_feeds/feeds/daily_volatility_manual_feed.py
telliot_feeds/feeds/diva_feed.py
telliot_feeds/feeds/diva_usd_feed.py
telliot_feeds/feeds/doge_usd_feed.py
telliot_feeds/feeds/dot_usd_feed.py
telliot_feeds/feeds/eth_btc_feed.py
telliot_feeds/feeds/eth_jpy_feed.py
telliot_feeds/feeds/eth_usd_30day_volatility.py
telliot_feeds/feeds/eth_usd_feed.py
telliot_feeds/feeds/eul_usd_feed.py
telliot_feeds/feeds/eur_usd_feed.py
telliot_feeds/feeds/evm_call_feed.py
telliot_feeds/feeds/fil_usd_feed.py
bctsag_telliotfeeds-1.0.1.dist-info/METADATA
bctsag_telliotfeeds-1.0.1.dist-info/WHEEL
bctsag_telliotfeeds-1.0.1.dist-info/entry_points.txt
bctsag_telliotfeeds-1.0.1.dist-info/top_level.txt
bctsag_telliotfeeds-1.0.1.dist-info/RECORD
